libmm/__init__.py
libmm/checks.py
libmm/config.py
libmm/data/d3fend.json
libmm/data/enterprise.json
libmm/data/tids.txt
libmm/extension.py
libmm/extensions/__init__.py
libmm/extensions/arbitrageur.py
libmm/extensions/attackmigrate.py
libmm/extensions/graphviz.py
libmm/extensions/guidance.py
libmm/extensions/partials.py
libmm/extensions/sigma.py
libmm/extensions/vectr.py
libmm/index.py
libmm/inject.py
libmm/log.py
libmm/mitre.py
libmm/scripts/__init__.py
libmm/scripts/mmarbitrageur/__init__.py
libmm/scripts/mmarbitrageur/shared.py
libmm/scripts/mmarbitrageur.py
libmm/scripts/mmcli.py
libmm/scripts/mmdarkpool/templates/base.html.j2
libmm/scripts/mmdarkpool/templates/blueprint.html.j2
libmm/scripts/mmdarkpool/templates/blueprints.html.j2
libmm/scripts/mmdarkpool/templates/variant.html.j2
libmm/scripts/mmdarkpool/templates/variants.html.j2
libmm/scripts/mmdarkpool.py
libmm/scripts/shared.py
libmm/selectors.py
libmm/sql.py
libmm/type.py
libmm/utils.py
marketmaker-1.12.0.dist-info/LICENSE-3P.txt
marketmaker-1.12.0.dist-info/LICENSE.txt
marketmaker-1.12.0.dist-info/METADATA
marketmaker-1.12.0.dist-info/WHEEL
marketmaker-1.12.0.dist-info/entry_points.txt
marketmaker-1.12.0.dist-info/RECORD
