Metadata-Version: 2.1
Name: marketmaker
Version: 1.12.0
Summary: Suite of tools for managing and creating attack plans
License: AGPL-3.0-only
Author: 2XXE
Author-email: root@example.com
Requires-Python: >=3.8,<4.0
Classifier: License :: OSI Approved :: GNU Affero General Public License v3
Classifier: Programming Language :: Python :: 3
Classifier: Programming Language :: Python :: 3.8
Classifier: Programming Language :: Python :: 3.9
Classifier: Programming Language :: Python :: 3.10
Classifier: Programming Language :: Python :: 3.11
Classifier: Programming Language :: Python :: 3.12
Classifier: Programming Language :: Python :: 3.13
Requires-Dist: click (>=8.1.3,<9.0.0)
Requires-Dist: graphviz (>=0.20.1,<0.21.0)
Requires-Dist: pydantic (>=1.10.7,<2.0.0)
Requires-Dist: pysigma (>=0.11.0,<0.12.0)
Requires-Dist: ruamel.yaml (>=0.17.21,<0.18.0)
Requires-Dist: sqlmodel (>=0.0.8,<0.0.9)
Requires-Dist: stix2 (>=3.0.1,<4.0.0)
